torque/__init__.py
torque/torque.py
torque/torque_user.py
torque/version.py
torque_python-1.1.0.dist-info/METADATA
torque_python-1.1.0.dist-info/RECORD
torque_python-1.1.0.dist-info/WHEEL
torque_python-1.1.0.dist-info/top_level.txt
