Metadata-Version: 2.1
Name: torque-python
Version: 1.1.0
Summary: Torque library.
Home-page: https://github.com/torquecloud/torque-python
Author: Torque, Inc.
Author-email: development@torque.cloud
License: UNKNOWN
Platform: UNKNOWN
Classifier: Programming Language :: Python :: 3
Classifier: License :: OSI Approved :: MIT License
Classifier: Operating System :: OS Independent
Requires-Python: >=3.6
Requires-Dist: requests (>=2.13.0)
